zhuntr-0.0.4.dist-info/METADATA
zhuntr-0.0.4.dist-info/WHEEL
zhuntr-0.0.4.dist-info/licenses/LICENSE
zhuntrs/__init__.py
zhuntrs/zhuntrs.cpython-39-aarch64-linux-gnu.so
zhuntr-0.0.4.dist-info/RECORD
