Metadata-Version: 2.3
Name: zhuntr
Version: 0.0.4
Classifier: Programming Language :: Rust
Classifier: Programming Language :: Python :: Implementation :: CPython
Classifier: Programming Language :: Python :: Implementation :: PyPy
License-File: LICENSE
Summary: Z-Hunt[rs] is a Rust port of the Z-Hunt algorithm for predicting the propensity of DNA to adopt a left-handed Z-DNA conformation.
Author: Aleksandr Fedorov
License: MIT
Requires-Python: >=3.8
Project-URL: Source Code, https://github.com/nucleohub/zhuntr
